{"gadgets":
 [{"y": 35,
   "x": 100,
   "output":
   {"app":
    {"label": "r",
     "args":
     [{"app": {"label": "3", "args": []}},
      {"app": {"label": "2", "args": []}}]}},
   "isAxiom": false,
   "inputs": [],
   "id": "gadget_#[0, 0]"},
  {"y": 47,
   "x": 50,
   "output":
   {"app":
    {"label": "g",
     "args":
     [{"var": {"name": "E_0"}},
      {"app": {"label": "2", "args": []}},
      {"app": {"label": "1", "args": []}}]}},
   "isAxiom": false,
   "inputs":
   [{"app":
     {"label": "r",
      "args":
      [{"app": {"label": "3", "args": []}},
       {"app": {"label": "2", "args": []}}]}}],
   "id": "gadget_#[0]"},
  {"y": 130,
   "x": 50,
   "output":
   {"app":
    {"label": "r",
     "args":
     [{"app": {"label": "2", "args": []}},
      {"app": {"label": "1", "args": []}}]}},
   "isAxiom": false,
   "inputs": [],
   "id": "gadget_#[1]"},
  {"y": 200,
   "x": 50,
   "output":
   {"app":
    {"label": "r",
     "args":
     [{"app": {"label": "4", "args": []}},
      {"app": {"label": "3", "args": []}}]}},
   "isAxiom": false,
   "inputs": [],
   "id": "gadget_#[2]"},
  {"y": 117,
   "x": 0,
   "output":
   {"app":
    {"label": "g",
     "args":
     [{"app": {"label": "4", "args": []}},
      {"app": {"label": "2", "args": []}},
      {"app": {"label": "2", "args": []}}]}},
   "isAxiom": false,
   "inputs":
   [{"app":
     {"label": "g",
      "args":
      [{"var": {"name": "E_0"}},
       {"app": {"label": "2", "args": []}},
       {"app": {"label": "1", "args": []}}]}},
    {"app":
     {"label": "r",
      "args":
      [{"app": {"label": "2", "args": []}},
       {"app": {"label": "1", "args": []}}]}},
    {"app":
     {"label": "r",
      "args":
      [{"app": {"label": "4", "args": []}},
       {"app": {"label": "3", "args": []}}]}}],
   "id": "gadget_#[]"}],
 "edges":
 [{"targetPosition": 0,
   "target": "gadget_#[0, 0]",
   "source": "gadget_#[0]",
   "id": "edge_#[0]_0"},
  {"targetPosition": 0,
   "target": "gadget_#[0]",
   "source": "gadget_#[]",
   "id": "edge_#[]_0"},
  {"targetPosition": 1,
   "target": "gadget_#[1]",
   "source": "gadget_#[]",
   "id": "edge_#[]_1"},
  {"targetPosition": 2,
   "target": "gadget_#[2]",
   "source": "gadget_#[]",
   "id": "edge_#[]_2"}]}